pyth4mini/__init__.py
pyth4mini/core.py
python4mini-0.1.1.dist-info/licenses/LICENSE
python4mini-0.1.1.dist-info/METADATA
python4mini-0.1.1.dist-info/WHEEL
python4mini-0.1.1.dist-info/top_level.txt
python4mini-0.1.1.dist-info/RECORD
