Metadata-Version: 2.4
Name: python4mini
Version: 0.1.1
Summary: Python4 MINI - Python with the addition of new functions to make life easier for programmers
Home-page: 
Author: KsDev
Author-email: contatoksdev@tutamail.com
Classifier: Programming Language :: Python :: 3
Classifier: License :: OSI Approved :: MIT License
Classifier: Operating System :: OS Independent
Requires-Python: >=3.7
License-File: LICENSE
Dynamic: license-file
